Metadata-Version: 2.1
Name: valgard
Version: 0.2.1
Summary: The official client for the Valueguard API
Home-page: https://github.com/Valueguard-Index-Sweden/valueguard-python-client
Author: Valueguard
Author-email: info@valueguard.se
License: MIT
Classifier: Programming Language :: Python :: 3.7
